.gitignore
.gitlab-ci.yml
.gitmodules
.pylintrc
COPYING.LGPLv3
Makefile
NEWS.txt
README.md
conf.py
index.rst
mkpinmux.sh
mypy.ini
setup.py
Waveforms/.gitkeep
doc/div_pipeline_loop_model/.gitignore
doc/div_pipeline_loop_model/README.md
doc/div_pipeline_loop_model/index.html
doc/div_pipeline_loop_model/tsconfig.json
doc/div_pipeline_loop_model/built/.gitkeep
doc/div_pipeline_loop_model/src/main.ts
src/libresoc.egg-info/PKG-INFO
src/libresoc.egg-info/SOURCES.txt
src/libresoc.egg-info/dependency_links.txt
src/libresoc.egg-info/not-zip-safe
src/libresoc.egg-info/requires.txt
src/libresoc.egg-info/top_level.txt
src/soc/__init__.py
src/soc/abstest.py
src/soc/array_test.py
src/soc/consts.py
src/soc/cz.py
src/soc/elif_bug.py
src/soc/frame.py
src/soc/idecode.py
src/soc/shifttest.py
src/soc/test.py
src/soc/testcls.py
src/soc/testinject.py
src/soc/TestUtil/__init__.py
src/soc/TestUtil/test_helper.py
src/soc/bus/SPBlock512W64B8W.py
src/soc/bus/__init__.py
src/soc/bus/simple_gpio.py
src/soc/bus/sram.py
src/soc/bus/wb_downconvert.py
src/soc/bus/test/__init__.py
src/soc/bus/test/test_minerva.py
src/soc/bus/test/test_sram_wb_downconvert.py
src/soc/bus/test/test_sram_wishbone.py
src/soc/bus/test/wb_rw.py
src/soc/clock/__init__.py
src/soc/clock/dummypll.py
src/soc/clock/select.py
src/soc/config/__init__.py
src/soc/config/endian.py
src/soc/config/ifetch.py
src/soc/config/loadstore.py
src/soc/config/pinouts.py
src/soc/config/state.py
src/soc/config/test/__init__.py
src/soc/config/test/test_fetch.py
src/soc/config/test/test_loadstore.py
src/soc/config/test/test_pi2ls.py
src/soc/debug/__init__.py
src/soc/debug/dmi.py
src/soc/debug/dmi2jtag.py
src/soc/debug/firmware_upload.py
src/soc/debug/jtag.py
src/soc/debug/jtagutils.py
src/soc/debug/ls180_pins.py
src/soc/debug/test/dmi_sim.py
src/soc/debug/test/idcode_test2.svf
src/soc/debug/test/jtagremote.py
src/soc/debug/test/openocd.cfg
src/soc/debug/test/openocd_test.sh
src/soc/debug/test/test_jtag_tap.py
src/soc/debug/test/test_jtag_tap_srv.py
src/soc/decoder/.gitignore
src/soc/decoder/__init__.py
src/soc/decoder/astPrinter.py
src/soc/decoder/decode2execute1.py
src/soc/decoder/helpers.py
src/soc/decoder/orderedset.py
src/soc/decoder/power_decoder.py
