Metadata-Version: 2.1
Name: libresoc
Version: 0.0.1
Summary: A nmigen-based OpenPOWER multi-issue Hybrid 3D CPU-VPU-GPU
Home-page: http://git.libre-soc.org/?p=soc
Author: Luke Kenneth Casson Leighton
Author-email: lkcl@libre-soc.org
License: LGPLv3+
Keywords: nmigen ieee754 libre-soc soc
Platform: UNKNOWN
Classifier: Topic :: Software Development
Classifier: License :: OSI Approved :: GNU Lesser General Public License v3 or later (LGPLv3+)
Classifier: Programming Language :: Python :: 3
Classifier: Operating System :: OS Independent
